CHANGELOG.rst
examples/chat_example.png
examples/count-dist.png
examples/days.png
examples/history.png
examples/hours.png
examples/titles.png
examples/week.png
telegram_stats_bot/__init__.py
telegram_stats_bot/db.py
telegram_stats_bot/json_dump_parser.py
telegram_stats_bot/log_storage.py
telegram_stats_bot/main.py
telegram_stats_bot/parse.py
telegram_stats_bot/stats.py
telegram_stats_bot/utils.py
telegram_stats_bot-0.8.1.dist-info/LICENSE
telegram_stats_bot-0.8.1.dist-info/METADATA
telegram_stats_bot-0.8.1.dist-info/WHEEL
telegram_stats_bot-0.8.1.dist-info/RECORD
