Metadata-Version: 2.1
Name: telegram-stats-bot
Version: 0.8.1
Summary: A logging and statistics bot for Telegram based on python-telegram-bot.
Home-page: https://github.com/mkdryden/telegram-stats-bot
License: GPL-3.0-or-later
Author: Michael DM Dryden
Author-email: mk.dryden@utoronto.ca
Requires-Python: >=3.9,<3.12
Classifier: License :: OSI Approved :: GNU General Public License v3 or later (GPLv3+)
Classifier: Programming Language :: Python :: 3
Classifier: Programming Language :: Python :: 3.9
Classifier: Programming Language :: Python :: 3.10
Classifier: Programming Language :: Python :: 3.11
Requires-Dist: SQLAlchemy (>=2.0.23,<3.0.0)
Requires-Dist: SQLAlchemy-Utils (>=0.41,<0.42)
Requires-Dist: appdirs (>=1.4.4,<2.0.0)
Requires-Dist: matplotlib (>=3.8,<4.0)
Requires-Dist: numpy (>=1.26.1,<2.0.0)
Requires-Dist: pandas (>=2.1,<3.0)
Requires-Dist: psycopg[binary] (>=3.1.12,<4.0.0)
Requires-Dist: pytest (>=7.4.3,<8.0.0)
Requires-Dist: python-telegram-bot[job-queue] (>=20.6,<21.0)
Requires-Dist: seaborn (>=0.13,<0.14)
Requires-Dist: single-source (>=0.3.0,<0.4.0)
Requires-Dist: typer (>=0.9.0,<0.10.0)
Project-URL: Repository, https://github.com/mkdryden/telegram-stats-bot
